README.md
setup.cfg
setup.py
xaptum/__init__.py
xaptum/tpm/__init__.py
xaptum/tpm/_extra_search_dir.py
xaptum/tpm/wrapper.py
xaptum_tpm_python.egg-info/PKG-INFO
xaptum_tpm_python.egg-info/SOURCES.txt
xaptum_tpm_python.egg-info/dependency_links.txt
xaptum_tpm_python.egg-info/top_level.txt