Metadata-Version: 1.0
Name: xaptum-tpm-python
Version: 0.4.0
Summary: Python wrapper for Xaptum TPM
Home-page: https://github.com/xaptum/xaptum-tpm-python
Author: Xaptum, Inc.
Author-email: sales@xaptum.com
License: Apache 2.0
Platform: UNKNOWN
